gencoder/__init__.py
gencoder/polycoder.py
gencoder/source.py
gencoder-0.2.2.dist-info/METADATA
gencoder-0.2.2.dist-info/WHEEL
gencoder-0.2.2.dist-info/top_level.txt
gencoder-0.2.2.dist-info/RECORD
