Metadata-Version: 2.1
Name: gencoder
Version: 0.2.2
Summary: Google Polyline Encoding Helper Package
Home-page: UNKNOWN
Author: Rachit Bhargava
Author-email: rachitbhargava99@gmail.com
License: UNKNOWN
Keywords: google polyline encoding
Platform: UNKNOWN
Classifier: Development Status :: 3 - Alpha
Classifier: Intended Audience :: Developers
Classifier: Programming Language :: Python :: 3.5
Classifier: Programming Language :: Python :: 3.6
Classifier: Programming Language :: Python :: 3.7
Classifier: Operating System :: OS Independent
Requires-Python: ~=3.5
